{
  "date": "20260318",
  "type": "사전규격",
  "total": 38,
  "confirmed_count": 11,
  "review_count": 18,
  "generated_at": "2026-03-18T21:42:56.221269",
  "confirmed": [
    {
      "검색키워드": "타당성",
      "사전규격등록번호": "R26BD00198933",
      "사업명(품명)": "서울시 기술교육원 남부캠퍼스 부지 기본구상 및 타당성 검토 용역",
      "발주기관": "군포도시공사",
      "수요기관": "군포도시공사",
      "배정예산액(원)": "650,000,000",
      "등록일시": "2026-03-18 15:07:35",
      "의견등록마감일": "2026-03-23 23:59:00",
      "납품기한": "",
      "SW사업여부": "N",
      "공고번호": "",
      "참조번호": "개발사업부-330",
      "규격서URL": "https://www.g2b.go.kr/pn/pnz/pnza/UntyAtchFile/downloadFile.do?bfSpecRegNo=R26BD00198933&fileType=BFDTL&fileSeq=1",
      "_matched": "기본구상"
    },
    {
      "검색키워드": "타당성",
      "사전규격등록번호": "R26BD00198899",
      "사업명(품명)": "인천1호선 무인운행시스템 도입 타당성조사 연구용역",
      "발주기관": "인천교통공사",
      "수요기관": "인천교통공사",
      "배정예산액(원)": "445,000,000",
      "등록일시": "2026-03-18 14:46:25",
      "의견등록마감일": "2026-03-23 23:59:00",
      "납품기한": "",
      "SW사업여부": "N",
      "공고번호": "",
      "참조번호": "차량2026-1279",
      "규격서URL": "https://www.g2b.go.kr/pn/pnz/pnza/UntyAtchFile/downloadFile.do?bfSpecRegNo=R26BD00198899&fileType=BFDTL&fileSeq=1",
      "_matched": "타당성조사"
    },
    {
      "검색키워드": "타당성",
      "사전규격등록번호": "R26BD00199270",
      "사업명(품명)": "[협상에의한계약]고흥군 소규모 관광단지 기본계획 수립 및 타당성 분석 연구용역",
      "발주기관": "전라남도 고흥군",
      "수요기관": "전라남도 고흥군",
      "배정예산액(원)": "100,000,000",
      "등록일시": "2026-03-18 19:43:08",
      "의견등록마감일": "2026-03-22 23:59:00",
      "납품기한": "",
      "SW사업여부": "N",
      "공고번호": "",
      "참조번호": "고흥군",
      "규격서URL": "https://www.g2b.go.kr/pn/pnz/pnza/UntyAtchFile/downloadFile.do?bfSpecRegNo=R26BD00199270&fileType=BFDTL&fileSeq=1",
      "_matched": "관광, 관광단지"
    },
    {
      "검색키워드": "타당성",
      "사전규격등록번호": "R26BD00198805",
      "사업명(품명)": "한강 낚시전용공간 개선 타당성조사 용역",
      "발주기관": "서울특별시 미래한강본부",
      "수요기관": "서울특별시 미래한강본부",
      "배정예산액(원)": "65,000,000",
      "등록일시": "2026-03-18 13:41:09",
      "의견등록마감일": "2026-03-23 23:59:00",
      "납품기한": "",
      "SW사업여부": "N",
      "공고번호": "",
      "참조번호": "수상관리과-2466",
      "규격서URL": "https://www.g2b.go.kr/pn/pnz/pnza/UntyAtchFile/downloadFile.do?bfSpecRegNo=R26BD00198805&fileType=BFDTL&fileSeq=1",
      "_matched": "타당성조사"
    },
    {
      "검색키워드": "기본계획",
      "사전규격등록번호": "R26BD00198875",
      "사업명(품명)": "고흥군 남열항 어촌뉴딜3.0사업(어촌회복형) 기본계획수립 용역",
      "발주기관": "한국농어촌공사 전남지역본부",
      "수요기관": "한국농어촌공사 전남지역본부",
      "배정예산액(원)": "290,400,000",
      "등록일시": "2026-03-18 14:33:04",
      "의견등록마감일": "2026-03-23 23:59:00",
      "납품기한": "",
      "SW사업여부": "N",
      "공고번호": "",
      "참조번호": "전남농지관리-",
      "규격서URL": "https://www.g2b.go.kr/pn/pnz/pnza/UntyAtchFile/downloadFile.do?bfSpecRegNo=R26BD00198875&fileType=BFDTL&fileSeq=1",
      "_matched": "어촌, 어촌뉴딜"
    },
    {
      "검색키워드": "설계",
      "사전규격등록번호": "R26BD00199199",
      "사업명(품명)": "색달 생수천 힐링센터 조성사업 기본 및 실시설계용역",
      "발주기관": "제주특별자치도 제주환경자원순환센터",
      "수요기관": "제주특별자치도 제주환경자원순환센터",
      "배정예산액(원)": "585,060,000",
      "등록일시": "2026-03-18 17:44:12",
      "의견등록마감일": "2026-03-23 23:59:00",
      "납품기한": "",
      "SW사업여부": "N",
      "공고번호": "",
      "참조번호": "제주환경자원순환센터-3114",
      "규격서URL": "https://www.g2b.go.kr/pn/pnz/pnza/UntyAtchFile/downloadFile.do?bfSpecRegNo=R26BD00199199&fileType=BFDTL&fileSeq=1",
      "_matched": "힐링"
    },
    {
      "검색키워드": "설계",
      "사전규격등록번호": "R26BD00199170",
      "사업명(품명)": "군산시 옥산면 농촌중심지활성화사업 세부설계 및 시행계획 수립 용역(제안공모)",
      "발주기관": "한국농어촌공사 전북지역본부",
      "수요기관": "한국농어촌공사 전북지역본부",
      "배정예산액(원)": "373,513,000",
      "등록일시": "2026-03-18 17:27:25",
      "의견등록마감일": "2026-03-23 23:59:00",
      "납품기한": "",
      "SW사업여부": "N",
      "공고번호": "",
      "참조번호": "전북농지관리-2725",
      "규격서URL": "https://www.g2b.go.kr/pn/pnz/pnza/UntyAtchFile/downloadFile.do?bfSpecRegNo=R26BD00199170&fileType=BFDTL&fileSeq=1",
      "_matched": "농촌"
    },
    {
      "검색키워드": "설계",
      "사전규격등록번호": "R26BD00198975",
      "사업명(품명)": "만의공원 공원조성계획 변경 및 실시설계 용역",
      "발주기관": "경기도 화성시 공원녹지사업소",
      "수요기관": "경기도 화성시 공원녹지사업소",
      "배정예산액(원)": "330,539,000",
      "등록일시": "2026-03-18 15:36:56",
      "의견등록마감일": "2026-03-23 23:59:00",
      "납품기한": "",
      "SW사업여부": "N",
      "공고번호": "",
      "참조번호": "공원조성과-2624",
      "규격서URL": "https://www.g2b.go.kr/pn/pnz/pnza/UntyAtchFile/downloadFile.do?bfSpecRegNo=R26BD00198975&fileType=BFDTL&fileSeq=1",
      "_matched": "공원, 조성계획"
    },
    {
      "검색키워드": "설계",
      "사전규격등록번호": "R26BD00199072",
      "사업명(품명)": "사방기념공원 조성계획(변경) 및 실시설계 용역",
      "발주기관": "경상북도 포항시",
      "수요기관": "경상북도 포항시 푸른도시사업단",
      "배정예산액(원)": "193,200,000",
      "등록일시": "2026-03-18 16:36:18",
      "의견등록마감일": "2026-03-23 23:59:00",
      "납품기한": "",
      "SW사업여부": "N",
      "공고번호": "",
      "참조번호": "재정관리과-10704",
      "규격서URL": "https://www.g2b.go.kr/pn/pnz/pnza/UntyAtchFile/downloadFile.do?bfSpecRegNo=R26BD00199072&fileType=BFDTL&fileSeq=1",
      "_matched": "공원, 조성계획"
    },
    {
      "검색키워드": "설계",
      "사전규격등록번호": "R26BD00199297",
      "사업명(품명)": "2026년 기후대응도시숲 조성사업 실시설계용역",
      "발주기관": "충청남도 서산시",
      "수요기관": "충청남도 서산시",
      "배정예산액(원)": "67,440,000",
      "등록일시": "2026-03-18 22:04:26",
      "의견등록마감일": "2026-03-23 23:59:00",
      "납품기한": "",
      "SW사업여부": "N",
      "공고번호": "",
      "참조번호": "산림공원과-6078",
      "규격서URL": "https://www.g2b.go.kr/pn/pnz/pnza/UntyAtchFile/downloadFile.do?bfSpecRegNo=R26BD00199297&fileType=BFDTL&fileSeq=1",
      "_matched": "숲, 도시숲, 기후대응도시숲"
    },
    {
      "검색키워드": "설계",
      "사전규격등록번호": "R26BD00198647",
      "사업명(품명)": "2026학년도 서정대학교 AI 기반 진로 설계 로드맵 프로그램",
      "발주기관": "서정대학",
      "수요기관": "서정대학",
      "배정예산액(원)": "35,000,000",
      "등록일시": "2026-03-18 10:12:44",
      "의견등록마감일": "2026-03-23 23:59:00",
      "납품기한": "2026-07-14 00:00:00",
      "SW사업여부": "N",
      "공고번호": "",
      "참조번호": "행정처-2026-196",
      "규격서URL": "https://www.g2b.go.kr/pn/pnz/pnza/UntyAtchFile/downloadFile.do?bfSpecRegNo=R26BD00198647&fileType=BFDTL&fileSeq=1",
      "_matched": "로드"
    }
  ],
  "review": [
    {
      "검색키워드": "타당성",
      "사전규격등록번호": "R26BD00199084",
      "사업명(품명)": "김해-밀양 고속도로 타당성 조사(평가)",
      "발주기관": "조달청",
      "수요기관": "국토교통부",
      "배정예산액(원)": "2,451,000,000",
      "등록일시": "2026-03-18 16:41:45",
      "의견등록마감일": "2026-03-23 23:59:00",
      "납품기한": "",
      "SW사업여부": "N",
      "공고번호": "",
      "참조번호": "도로건설과-1095",
      "규격서URL": "https://www.g2b.go.kr/pn/pnz/pnza/UntyAtchFile/downloadFile.do?bfSpecRegNo=R26BD00199084&fileType=BFDTL&fileSeq=1"
    },
    {
      "검색키워드": "타당성",
      "사전규격등록번호": "R26BD00199082",
      "사업명(품명)": "생산기반정비사업 성과지표 개발 및 타당성 검증 연구 용역",
      "발주기관": "한국농어촌공사 농어촌연구원",
      "수요기관": "한국농어촌공사 농어촌연구원",
      "배정예산액(원)": "50,000,000",
      "등록일시": "2026-03-18 16:41:01",
      "의견등록마감일": "2026-03-23 23:59:00",
      "납품기한": "2026-11-30 00:00:00",
      "SW사업여부": "N",
      "공고번호": "",
      "참조번호": "연구지원-770",
      "규격서URL": "https://www.g2b.go.kr/pn/pnz/pnza/UntyAtchFile/downloadFile.do?bfSpecRegNo=R26BD00199082&fileType=BFDTL&fileSeq=1"
    },
    {
      "검색키워드": "기본계획",
      "사전규격등록번호": "R26BD00198520",
      "사업명(품명)": "2035년 대구도시관리계획 정비 용역",
      "발주기관": "대구광역시",
      "수요기관": "대구광역시",
      "배정예산액(원)": "1,500,000,000",
      "등록일시": "2026-03-18 08:07:31",
      "의견등록마감일": "2026-03-23 23:59:00",
      "납품기한": "",
      "SW사업여부": "N",
      "공고번호": "",
      "참조번호": "도시계획과",
      "규격서URL": "https://www.g2b.go.kr/pn/pnz/pnza/UntyAtchFile/downloadFile.do?bfSpecRegNo=R26BD00198520&fileType=BFDTL&fileSeq=1"
    },
    {
      "검색키워드": "기본계획",
      "사전규격등록번호": "R26BD00199158",
      "사업명(품명)": "도시계획정보체계(UPIS) 도형 및 속성자료 업데이트 및 유지관리 용역",
      "발주기관": "조달청 제주지방조달청",
      "수요기관": "제주특별자치도",
      "배정예산액(원)": "245,372,480",
      "등록일시": "2026-03-18 17:21:21",
      "의견등록마감일": "2026-03-23 23:59:00",
      "납품기한": "2026-12-31 00:00:00",
      "SW사업여부": "Y",
      "공고번호": "",
      "참조번호": "도시계획과-3012",
      "규격서URL": "https://www.g2b.go.kr/pn/pnz/pnza/UntyAtchFile/downloadFile.do?bfSpecRegNo=R26BD00199158&fileType=BFDTL&fileSeq=1"
    },
    {
      "검색키워드": "기본계획",
      "사전규격등록번호": "R26BD00198686",
      "사업명(품명)": "처분시설 종합개발계획 시나리오 구축 및 경제적 변동성 분석 용역",
      "발주기관": "한국원자력환경공단",
      "수요기관": "한국원자력환경공단",
      "배정예산액(원)": "219,367,255",
      "등록일시": "2026-03-18 10:52:08",
      "의견등록마감일": "2026-03-21 23:59:00",
      "납품기한": "",
      "SW사업여부": "N",
      "공고번호": "",
      "참조번호": "한국원자력환경공단 2026-032",
      "규격서URL": "https://www.g2b.go.kr/pn/pnz/pnza/UntyAtchFile/downloadFile.do?bfSpecRegNo=R26BD00198686&fileType=BFDTL&fileSeq=1"
    },
    {
      "검색키워드": "기본계획",
      "사전규격등록번호": "R26BD00198565",
      "사업명(품명)": "2030 의령군관리계획(재정비) 및 공업지역기본계획 수립 전략환경영향평가와 기후변화영향평가 용역",
      "발주기관": "경상남도 의령군",
      "수요기관": "경상남도 의령군",
      "배정예산액(원)": "168,611,000",
      "등록일시": "2026-03-18 09:26:38",
      "의견등록마감일": "2026-03-23 23:59:00",
      "납품기한": "",
      "SW사업여부": "N",
      "공고번호": "",
      "참조번호": "도시재생과-10445",
      "규격서URL": ""
    },
    {
      "검색키워드": "기본계획",
      "사전규격등록번호": "R26BD00198679",
      "사업명(품명)": "제5차 전북특별자치도 교통약자 이동편의 증진계획 및 교통안전 기본계획 수립 용역",
      "발주기관": "전북특별자치도",
      "수요기관": "전북특별자치도",
      "배정예산액(원)": "149,000,000",
      "등록일시": "2026-03-18 10:46:32",
      "의견등록마감일": "2026-03-21 23:59:00",
      "납품기한": "",
      "SW사업여부": "N",
      "공고번호": "",
      "참조번호": "교통정책과-5917",
      "규격서URL": "https://www.g2b.go.kr/pn/pnz/pnza/UntyAtchFile/downloadFile.do?bfSpecRegNo=R26BD00198679&fileType=BFDTL&fileSeq=1"
    },
    {
      "검색키워드": "기본계획",
      "사전규격등록번호": "R26BD00198695",
      "사업명(품명)": "제2차 부산광역시 화학물질 안전관리계획 수립",
      "발주기관": "부산광역시",
      "수요기관": "부산광역시",
      "배정예산액(원)": "90,000,000",
      "등록일시": "2026-03-18 11:03:10",
      "의견등록마감일": "2026-03-23 23:59:00",
      "납품기한": "",
      "SW사업여부": "N",
      "공고번호": "",
      "참조번호": "환경정책과-5635",
      "규격서URL": "https://www.g2b.go.kr/pn/pnz/pnza/UntyAtchFile/downloadFile.do?bfSpecRegNo=R26BD00198695&fileType=BFDTL&fileSeq=1"
    },
    {
      "검색키워드": "기본계획",
      "사전규격등록번호": "R26BD00199283",
      "사업명(품명)": "옹진군 제2차 인구감소지역대응 기본계획 수립용역",
      "발주기관": "인천광역시 옹진군",
      "수요기관": "인천광역시 옹진군",
      "배정예산액(원)": "57,000,000",
      "등록일시": "2026-03-18 20:21:03",
      "의견등록마감일": "2026-03-21 23:59:00",
      "납품기한": "",
      "SW사업여부": "N",
      "공고번호": "",
      "참조번호": "옹진군",
      "규격서URL": "https://www.g2b.go.kr/pn/pnz/pnza/UntyAtchFile/downloadFile.do?bfSpecRegNo=R26BD00199283&fileType=BFDTL&fileSeq=1"
    },
    {
      "검색키워드": "설계",
      "사전규격등록번호": "R26BD00199037",
      "사업명(품명)": "길곡증산하수관로정비사업기본및실시설계용역",
      "발주기관": "경상남도 창녕군",
      "수요기관": "경상남도 창녕군",
      "배정예산액(원)": "447,774,000",
      "등록일시": "2026-03-18 16:20:45",
      "의견등록마감일": "2026-03-23 23:59:00",
      "납품기한": "",
      "SW사업여부": "N",
      "공고번호": "",
      "참조번호": "창녕군수도과",
      "규격서URL": "https://www.g2b.go.kr/pn/pnz/pnza/UntyAtchFile/downloadFile.do?bfSpecRegNo=R26BD00199037&fileType=BFDTL&fileSeq=1"
    },
    {
      "검색키워드": "설계",
      "사전규격등록번호": "R26BD00198531",
      "사업명(품명)": "DMZ 특별전 전시연출 설계 및 제작·설치",
      "발주기관": "조달청 서울지방조달청",
      "수요기관": "문화체육관광부 대한민국역사박물관",
      "배정예산액(원)": "302,590,000",
      "등록일시": "2026-03-18 08:50:06",
      "의견등록마감일": "2026-03-23 23:59:00",
      "납품기한": "2026-09-22 00:00:00",
      "SW사업여부": "N",
      "공고번호": "",
      "참조번호": "전시운영과-212",
      "규격서URL": "https://www.g2b.go.kr/pn/pnz/pnza/UntyAtchFile/downloadFile.do?bfSpecRegNo=R26BD00198531&fileType=BFDTL&fileSeq=1"
    },
    {
      "검색키워드": "설계",
      "사전규격등록번호": "R26BD00198894",
      "사업명(품명)": "국도대체우회도로(남산-하양)상수관로 이설공사 실시설계 용역",
      "발주기관": "경상북도 경산시 맑은물사업본부 상수도과",
      "수요기관": "경상북도 경산시 맑은물사업본부 상수도과",
      "배정예산액(원)": "220,000,000",
      "등록일시": "2026-03-18 14:44:02",
      "의견등록마감일": "2026-03-23 23:59:00",
      "납품기한": "",
      "SW사업여부": "N",
      "공고번호": "",
      "참조번호": "상수도과-2200",
      "규격서URL": "https://www.g2b.go.kr/pn/pnz/pnza/UntyAtchFile/downloadFile.do?bfSpecRegNo=R26BD00198894&fileType=BFDTL&fileSeq=1"
    },
    {
      "검색키워드": "설계",
      "사전규격등록번호": "R26BD00199261",
      "사업명(품명)": "00부대 사령부 연구동 리모델링 설계용역",
      "발주기관": "국방부 국방정보본부 3275부대",
      "수요기관": "국방부 국방정보본부 3275부대",
      "배정예산액(원)": "197,478,000",
      "등록일시": "2026-03-18 18:58:27",
      "의견등록마감일": "2026-03-22 00:00:00",
      "납품기한": "",
      "SW사업여부": "N",
      "공고번호": "",
      "참조번호": "PS2026MDS2026-02507",
      "규격서URL": ""
    },
    {
      "검색키워드": "설계",
      "사전규격등록번호": "R26BD00199207",
      "사업명(품명)": "디지털트윈 기반 해사 서비스를 위한DevOps 체계 개발 및 MLOps 확장 설계 용역",
      "발주기관": "조달청 대전지방조달청",
      "수요기관": "한국해양과학기술원 부설 선박해양플랜트연구소",
      "배정예산액(원)": "161,526,000",
      "등록일시": "2026-03-18 17:49:45",
      "의견등록마감일": "2026-03-23 23:59:00",
      "납품기한": "",
      "SW사업여부": "Y",
      "공고번호": "",
      "참조번호": "2026-VC39-24",
      "규격서URL": "https://www.g2b.go.kr/pn/pnz/pnza/UntyAtchFile/downloadFile.do?bfSpecRegNo=R26BD00199207&fileType=BFDTL&fileSeq=1"
    },
    {
      "검색키워드": "설계",
      "사전규격등록번호": "R26BD00199056",
      "사업명(품명)": "개인정보보호 중심 설계 인증 서비스 지원 및 개선방안 연구용역",
      "발주기관": "조달청 서울지방조달청",
      "수요기관": "개인정보보호위원회",
      "배정예산액(원)": "151,595,000",
      "등록일시": "2026-03-18 16:30:18",
      "의견등록마감일": "2026-03-23 23:59:00",
      "납품기한": "2026-12-18 00:00:00",
      "SW사업여부": "N",
      "공고번호": "",
      "참조번호": "신기술개인정보과-306",
      "규격서URL": "https://www.g2b.go.kr/pn/pnz/pnza/UntyAtchFile/downloadFile.do?bfSpecRegNo=R26BD00199056&fileType=BFDTL&fileSeq=1"
    },
    {
      "검색키워드": "설계",
      "사전규격등록번호": "R26BD00198916",
      "사업명(품명)": "증평3일반산업단지 공업용수도 건설사업 실시설계용역",
      "발주기관": "충청북도 증평군",
      "수요기관": "충청북도 증평군",
      "배정예산액(원)": "132,990,000",
      "등록일시": "2026-03-18 14:55:49",
      "의견등록마감일": "2026-03-21 18:00:00",
      "납품기한": "",
      "SW사업여부": "N",
      "공고번호": "",
      "참조번호": "재무과-6606",
      "규격서URL": "https://www.g2b.go.kr/pn/pnz/pnza/UntyAtchFile/downloadFile.do?bfSpecRegNo=R26BD00198916&fileType=BFDTL&fileSeq=1"
    },
    {
      "검색키워드": "설계",
      "사전규격등록번호": "R26BD00198654",
      "사업명(품명)": "채취시료의 현장 검증을 위한 결합장치 설계 및 성능평가 연구용역",
      "발주기관": "한국원자력통제기술원",
      "수요기관": "한국원자력통제기술원",
      "배정예산액(원)": "48,000,000",
      "등록일시": "2026-03-18 10:20:17",
      "의견등록마감일": "2026-03-23 23:59:00",
      "납품기한": "",
      "SW사업여부": "N",
      "공고번호": "",
      "참조번호": "82094",
      "규격서URL": "https://www.g2b.go.kr/pn/pnz/pnza/UntyAtchFile/downloadFile.do?bfSpecRegNo=R26BD00198654&fileType=BFDTL&fileSeq=1"
    },
    {
      "검색키워드": "설계",
      "사전규격등록번호": "R26BD00199223",
      "사업명(품명)": "정책연구(국가 인재정책 지도 설계 및 정책 포트폴리오 구조 분석 연구)",
      "발주기관": "국가교육위원회",
      "수요기관": "국가교육위원회",
      "배정예산액(원)": "40,000,000",
      "등록일시": "2026-03-18 17:56:12",
      "의견등록마감일": "2026-03-23 23:59:00",
      "납품기한": "",
      "SW사업여부": "N",
      "공고번호": "",
      "참조번호": "교육발전총괄과-1314",
      "규격서URL": "https://www.g2b.go.kr/pn/pnz/pnza/UntyAtchFile/downloadFile.do?bfSpecRegNo=R26BD00199223&fileType=BFDTL&fileSeq=1"
    }
  ]
}