{
  "date": "20260303",
  "type": "발주계획",
  "total": 84,
  "generated_at": "2026-03-09T08:25:12.130046",
  "items": [
    {
      "검색키워드": "타당성",
      "사업명": "한국전통건축 아카이브센터 구축 사업 타당성 조사 및 기본계획 수립 용역",
      "발주기관": "국가유산청",
      "총괄기관": "국가유산청",
      "소관구분": "국가기관",
      "합계발주금액(원)": "200,000,000",
      "발주년도": "2026",
      "발주월": "03",
      "공종구분": "",
      "계약방법": "제한경쟁",
      "조달방식": "중앙조달",
      "업무유형": "신규",
      "게시일시": "2026-03-03 13:01:56",
      "담당부서": "수리기술과",
      "담당자": "이재권",
      "전화번호": "042-481-4970",
      "공고번호": ""
    },
    {
      "검색키워드": "기본계획",
      "사업명": "나주시 수도정비 기본계획(변경) 수립 및 상수도관망 기술진단 용역",
      "발주기관": "전라남도 나주시 상수도사업소",
      "총괄기관": "전라남도",
      "소관구분": "지방공기업",
      "합계발주금액(원)": "1,800,300,000",
      "발주년도": "2026",
      "발주월": "03",
      "공종구분": "",
      "계약방법": "지명경쟁",
      "조달방식": "자체조달",
      "업무유형": "신규",
      "게시일시": "2026-03-03 15:01:01",
      "담당부서": "상하수도과",
      "담당자": "정유미",
      "전화번호": "061-339-7643",
      "공고번호": "R26BK01364782000"
    },
    {
      "검색키워드": "기본계획",
      "사업명": "국수천 등 5개 하천기본계획(변경) 수립 용역",
      "발주기관": "울산광역시",
      "총괄기관": "울산광역시",
      "소관구분": "지방자치단체",
      "합계발주금액(원)": "718,000,000",
      "발주년도": "2026",
      "발주월": "03",
      "공종구분": "",
      "계약방법": "제한경쟁",
      "조달방식": "자체조달",
      "업무유형": "신규",
      "게시일시": "2026-03-03 16:25:34",
      "담당부서": "행정국 회계과",
      "담당자": "최창민",
      "전화번호": "052-229-0000",
      "공고번호": ""
    },
    {
      "검색키워드": "기본계획",
      "사업명": "제3차 강원특별자치도 광역건축기본계획 수립 연구용역",
      "발주기관": "강원특별자치도",
      "총괄기관": "강원특별자치도",
      "소관구분": "지방자치단체",
      "합계발주금액(원)": "120,000,000",
      "발주년도": "2026",
      "발주월": "03",
      "공종구분": "",
      "계약방법": "제한경쟁",
      "조달방식": "자체조달",
      "업무유형": "신규",
      "게시일시": "2026-03-03 16:00:27",
      "담당부서": "회계과",
      "담당자": "이종묵",
      "전화번호": "033-249-2890",
      "공고번호": ""
    },
    {
      "검색키워드": "기본계획",
      "사업명": "제5차 국어발전 기본계획 수립 연구",
      "발주기관": "문화체육관광부",
      "총괄기관": "문화체육관광부",
      "소관구분": "국가기관",
      "합계발주금액(원)": "60,000,000",
      "발주년도": "2026",
      "발주월": "03",
      "공종구분": "",
      "계약방법": "제한경쟁",
      "조달방식": "자체조달",
      "업무유형": "신규",
      "게시일시": "2026-03-03 09:12:21",
      "담당부서": "국어정책과",
      "담당자": "남미정",
      "전화번호": "044-203-2530",
      "공고번호": "R26BK01377117000"
    },
    {
      "검색키워드": "기본계획",
      "사업명": "동해시 교육발전 중장기 기본계획 수립 연구 용역",
      "발주기관": "강원특별자치도 동해시",
      "총괄기관": "강원특별자치도",
      "소관구분": "지방자치단체",
      "합계발주금액(원)": "50,000,000",
      "발주년도": "2026",
      "발주월": "03",
      "공종구분": "",
      "계약방법": "제한경쟁",
      "조달방식": "자체조달",
      "업무유형": "신규",
      "게시일시": "2026-03-03 17:40:33",
      "담당부서": "체육교육과",
      "담당자": "이태빈",
      "전화번호": "033-530-2351",
      "공고번호": "R26BK01365803000"
    },
    {
      "검색키워드": "기본계획",
      "사업명": "죽산면 취약지역 생활여건 개조사업 기본계획 수립",
      "발주기관": "전북특별자치도 김제시",
      "총괄기관": "전북특별자치도",
      "소관구분": "지방자치단체",
      "합계발주금액(원)": "48,000,000",
      "발주년도": "2026",
      "발주월": "03",
      "공종구분": "",
      "계약방법": "수의계약",
      "조달방식": "자체조달",
      "업무유형": "신규",
      "게시일시": "2026-03-03 07:29:45",
      "담당부서": "농촌활력과",
      "담당자": "전정호",
      "전화번호": "063-540-3656",
      "공고번호": "R26BK01363128000"
    },
    {
      "검색키워드": "기본계획",
      "사업명": "신평 용봉리 취약지역생활여건개조사업 기본계획수립 용역",
      "발주기관": "한국농어촌공사 경북지역본부 의성.군위지사",
      "총괄기관": "한국농어촌공사",
      "소관구분": "준정부기관",
      "합계발주금액(원)": "47,300,000",
      "발주년도": "2026",
      "발주월": "03",
      "공종구분": "",
      "계약방법": "수의계약",
      "조달방식": "자체조달",
      "업무유형": "신규",
      "게시일시": "2026-03-03 09:24:41",
      "담당부서": "농지은행관리부",
      "담당자": "김가현",
      "전화번호": "054-830-8116",
      "공고번호": "R26BK01363495000"
    },
    {
      "검색키워드": "기본계획",
      "사업명": "금곡2리 취약지역생활여건개조사업 기본계획수립 용역",
      "발주기관": "한국농어촌공사 경북지역본부 의성.군위지사",
      "총괄기관": "한국농어촌공사",
      "소관구분": "준정부기관",
      "합계발주금액(원)": "46,200,000",
      "발주년도": "2026",
      "발주월": "03",
      "공종구분": "",
      "계약방법": "수의계약",
      "조달방식": "자체조달",
      "업무유형": "신규",
      "게시일시": "2026-03-03 09:23:32",
      "담당부서": "농지은행관리부",
      "담당자": "김가현",
      "전화번호": "054-830-8116",
      "공고번호": "R26BK01363322000"
    },
    {
      "검색키워드": "기본계획",
      "사업명": "제5차 금정구 교통안전기본계획 수립 연구용역",
      "발주기관": "부산광역시 금정구",
      "총괄기관": "부산광역시",
      "소관구분": "지방자치단체",
      "합계발주금액(원)": "30,000,000",
      "발주년도": "2026",
      "발주월": "03",
      "공종구분": "",
      "계약방법": "수의계약",
      "조달방식": "자체조달",
      "업무유형": "신규",
      "게시일시": "2026-03-03 10:13:45",
      "담당부서": "교통행정과",
      "담당자": "이소정",
      "전화번호": "051-519-4552",
      "공고번호": "R26BK01367162000"
    },
    {
      "검색키워드": "설계",
      "사업명": "도신 자연재해위험개선지구 정비사업 기본 및 실시설계 용역",
      "발주기관": "경기도 연천군",
      "총괄기관": "경기도",
      "소관구분": "지방자치단체",
      "합계발주금액(원)": "3,742,530,000",
      "발주년도": "2026",
      "발주월": "03",
      "공종구분": "",
      "계약방법": "일반경쟁",
      "조달방식": "자체조달",
      "업무유형": "신규",
      "게시일시": "2026-03-03 14:33:27",
      "담당부서": "안전총괄과",
      "담당자": "주문수",
      "전화번호": "031-839-2412",
      "공고번호": "R26BK01364663000"
    },
    {
      "검색키워드": "설계",
      "사업명": "옥매지구 풍수해생활권 종합정비사업 기본 및 실시설계 용역",
      "발주기관": "경상남도 함양군",
      "총괄기관": "경상남도",
      "소관구분": "지방자치단체",
      "합계발주금액(원)": "2,926,418,000",
      "발주년도": "2026",
      "발주월": "03",
      "공종구분": "",
      "계약방법": "지명경쟁",
      "조달방식": "자체조달",
      "업무유형": "신규",
      "게시일시": "2026-03-03 17:21:48",
      "담당부서": "안전총괄과",
      "담당자": "복구지원담당",
      "전화번호": "055-960-4323",
      "공고번호": "R26BK01365702002"
    },
    {
      "검색키워드": "설계",
      "사업명": "추성지구 풍수해생활권 종합정비사업 기본 및 실시설계 용역",
      "발주기관": "경상남도 함양군",
      "총괄기관": "경상남도",
      "소관구분": "지방자치단체",
      "합계발주금액(원)": "2,316,968,000",
      "발주년도": "2026",
      "발주월": "03",
      "공종구분": "",
      "계약방법": "지명경쟁",
      "조달방식": "자체조달",
      "업무유형": "신규",
      "게시일시": "2026-03-03 17:45:32",
      "담당부서": "안전총괄과",
      "담당자": "복구지원담당",
      "전화번호": "055-960-4320",
      "공고번호": "R26BK01365819001"
    },
    {
      "검색키워드": "설계",
      "사업명": "나주 문평 자연재해위험개선지구 정비사업 기본 및 실시설계 용역(PQ 후 지명경쟁)",
      "발주기관": "전라남도",
      "총괄기관": "전라남도",
      "소관구분": "지방자치단체",
      "합계발주금액(원)": "1,947,616,000",
      "발주년도": "2026",
      "발주월": "03",
      "공종구분": "",
      "계약방법": "일반경쟁",
      "조달방식": "자체조달",
      "업무유형": "신규",
      "게시일시": "2026-03-03 20:07:02",
      "담당부서": "회계과 계약팀",
      "담당자": "이수연",
      "전화번호": "061-286-3678",
      "공고번호": ""
    },
    {
      "검색키워드": "설계",
      "사업명": "일직동 생활문화복합센터 건립공사 기본 및 실시설계용역",
      "발주기관": "경기도 광명시",
      "총괄기관": "경기도",
      "소관구분": "지방자치단체",
      "합계발주금액(원)": "1,426,000,000",
      "발주년도": "2026",
      "발주월": "03",
      "공종구분": "",
      "계약방법": "일반경쟁",
      "조달방식": "자체조달",
      "업무유형": "신규",
      "게시일시": "2026-03-03 17:32:19",
      "담당부서": "광명시 건설지원과",
      "담당자": "담당자",
      "전화번호": "02-2680-2379",
      "공고번호": ""
    },
    {
      "검색키워드": "설계",
      "사업명": "고정지구 급경사지 붕괴위험지구 정비사업 기본 및 실시설계 용역",
      "발주기관": "경상남도 함양군",
      "총괄기관": "경상남도",
      "소관구분": "지방자치단체",
      "합계발주금액(원)": "1,290,190,000",
      "발주년도": "2026",
      "발주월": "03",
      "공종구분": "",
      "계약방법": "지명경쟁",
      "조달방식": "자체조달",
      "업무유형": "신규",
      "게시일시": "2026-03-03 16:25:41",
      "담당부서": "안전총괄과",
      "담당자": "복구지원담당",
      "전화번호": "055-960-4323",
      "공고번호": "R26BK01365345001"
    },
    {
      "검색키워드": "설계",
      "사업명": "진주시 상대배수지 확장사업 기본 및 실시설계용역 ",
      "발주기관": "경상남도 진주시",
      "총괄기관": "경상남도",
      "소관구분": "지방자치단체",
      "합계발주금액(원)": "1,156,200,000",
      "발주년도": "2026",
      "발주월": "03",
      "공종구분": "",
      "계약방법": "일반경쟁",
      "조달방식": "자체조달",
      "업무유형": "신규",
      "게시일시": "2026-03-03 17:45:19",
      "담당부서": "수도과",
      "담당자": "황지은",
      "전화번호": "055-749-6807",
      "공고번호": ""
    },
    {
      "검색키워드": "설계",
      "사업명": "1단계 장기미집행 도시계획도로 도시관리계획결정(변경) 및 실시설계용역",
      "발주기관": "경기도 광주시",
      "총괄기관": "경기도",
      "소관구분": "지방자치단체",
      "합계발주금액(원)": "798,852,000",
      "발주년도": "2026",
      "발주월": "03",
      "공종구분": "",
      "계약방법": "일반경쟁",
      "조달방식": "자체조달",
      "업무유형": "신규",
      "게시일시": "2026-03-03 21:18:36",
      "담당부서": "도로사업과",
      "담당자": "이종훈",
      "전화번호": "031-760-4699",
      "공고번호": "R26BK01366203001"
    },
    {
      "검색키워드": "설계",
      "사업명": "(PQ) 살구미지구 친환경 친수공간 조성사업 기본 및 실시설계 용역 ",
      "발주기관": "강원특별자치도 인제군",
      "총괄기관": "강원특별자치도",
      "소관구분": "지방자치단체",
      "합계발주금액(원)": "797,870,000",
      "발주년도": "2026",
      "발주월": "03",
      "공종구분": "",
      "계약방법": "일반경쟁",
      "조달방식": "자체조달",
      "업무유형": "신규",
      "게시일시": "2026-03-03 17:56:21",
      "담당부서": "건설과",
      "담당자": "이규호",
      "전화번호": "033-460-2095",
      "공고번호": ""
    },
    {
      "검색키워드": "설계",
      "사업명": "노후 송수관로 정비사업 실시설계용역",
      "발주기관": "경상북도 구미시 상하수도사업본부",
      "총괄기관": "경상북도",
      "소관구분": "지방자치단체",
      "합계발주금액(원)": "698,000,000",
      "발주년도": "2026",
      "발주월": "03",
      "공종구분": "",
      "계약방법": "지명경쟁",
      "조달방식": "자체조달",
      "업무유형": "신규",
      "게시일시": "2026-03-03 10:59:46",
      "담당부서": "수도과",
      "담당자": "이병수",
      "전화번호": "054-480-4442",
      "공고번호": ""
    },
    {
      "검색키워드": "설계",
      "사업명": "갯벌랜드, 청천리 하수관로 정비사업 기본 및 실시설계용역",
      "발주기관": "전라남도 무안군 상하수도사업소",
      "총괄기관": "전라남도",
      "소관구분": "지방자치단체",
      "합계발주금액(원)": "694,520,000",
      "발주년도": "2026",
      "발주월": "03",
      "공종구분": "",
      "계약방법": "일반경쟁",
      "조달방식": "자체조달",
      "업무유형": "장기",
      "게시일시": "2026-03-03 11:34:41",
      "담당부서": "무안군 상하수도사업소 하수도시설팀",
      "담당자": "오현진",
      "전화번호": "061-450-4120",
      "공고번호": "R26BK01363923001"
    },
    {
      "검색키워드": "설계",
      "사업명": "삼거, 원호덕(하늘소)마을 하수관로 및 양악지구 농어촌마을하수도 정비사업 기본 및 실시설계 용역",
      "발주기관": "전북특별자치도 장수군",
      "총괄기관": "전북특별자치도",
      "소관구분": "지방자치단체",
      "합계발주금액(원)": "544,093,000",
      "발주년도": "2026",
      "발주월": "03",
      "공종구분": "",
      "계약방법": "일반경쟁",
      "조달방식": "자체조달",
      "업무유형": "신규",
      "게시일시": "2026-03-03 10:16:01",
      "담당부서": "물관리과",
      "담당자": "정병준",
      "전화번호": "063-350-2902",
      "공고번호": "R26BK01375867000"
    },
    {
      "검색키워드": "설계",
      "사업명": "26-M-00부대 해수급수관로 개선 등 8건 설계용역(C004)",
      "발주기관": "국방부 국군재정관리단",
      "총괄기관": "국방부",
      "소관구분": "국가기관",
      "합계발주금액(원)": "500,695,000",
      "발주년도": "2026",
      "발주월": "03",
      "공종구분": "",
      "계약방법": "일반경쟁",
      "조달방식": "자체조달",
      "업무유형": "신규",
      "게시일시": "2026-03-03 14:30:01",
      "담당부서": "제2공사계약과",
      "담당자": "이신동",
      "전화번호": "02-3146-6615",
      "공고번호": "R26BK01364612000"
    },
    {
      "검색키워드": "설계",
      "사업명": "구로동 농어촌마을 마을하수도 정비사업 기본 및 실시설계용역",
      "발주기관": "전라남도 무안군 상하수도사업소",
      "총괄기관": "전라남도",
      "소관구분": "지방자치단체",
      "합계발주금액(원)": "438,902,000",
      "발주년도": "2026",
      "발주월": "03",
      "공종구분": "",
      "계약방법": "일반경쟁",
      "조달방식": "자체조달",
      "업무유형": "장기",
      "게시일시": "2026-03-03 11:12:24",
      "담당부서": "상하수도사업소 하수도시설팀",
      "담당자": "오현진",
      "전화번호": "061-450-4120",
      "공고번호": "R26BK01363828001"
    },
    {
      "검색키워드": "설계",
      "사업명": "정관 노인복지관~윗골공원 보행교 설치 기본 및 실시설계 용역",
      "발주기관": "부산광역시 기장군",
      "총괄기관": "부산광역시",
      "소관구분": "지방자치단체",
      "합계발주금액(원)": "300,000,000",
      "발주년도": "2026",
      "발주월": "03",
      "공종구분": "",
      "계약방법": "제한경쟁",
      "조달방식": "자체조달",
      "업무유형": "신규",
      "게시일시": "2026-03-03 13:40:48",
      "담당부서": "건설과",
      "담당자": "이민수",
      "전화번호": "051-709-4445",
      "공고번호": "R26BK01364298000"
    },
    {
      "검색키워드": "설계",
      "사업명": "학산지구 양수장시설개선사업 세부설계 용역",
      "발주기관": "한국농어촌공사 전남지역본부",
      "총괄기관": "한국농어촌공사",
      "소관구분": "준정부기관",
      "합계발주금액(원)": "243,941,000",
      "발주년도": "2026",
      "발주월": "03",
      "공종구분": "",
      "계약방법": "제한경쟁",
      "조달방식": "자체조달",
      "업무유형": "신규",
      "게시일시": "2026-03-03 15:46:39",
      "담당부서": "농지은행관리부",
      "담당자": "류선아",
      "전화번호": "062-958-2310",
      "공고번호": ""
    },
    {
      "검색키워드": "설계",
      "사업명": "본덕1지구 양수장시설개선사업 세부설계 용역",
      "발주기관": "한국농어촌공사 전남지역본부",
      "총괄기관": "한국농어촌공사",
      "소관구분": "준정부기관",
      "합계발주금액(원)": "234,715,000",
      "발주년도": "2026",
      "발주월": "03",
      "공종구분": "",
      "계약방법": "제한경쟁",
      "조달방식": "자체조달",
      "업무유형": "신규",
      "게시일시": "2026-03-03 15:45:17",
      "담당부서": "농지은행관리부",
      "담당자": "류선아",
      "전화번호": "062-958-2310",
      "공고번호": ""
    },
    {
      "검색키워드": "설계",
      "사업명": "관내 시설물 내진보강 공사 등 실시설계용역",
      "발주기관": "국토교통부 부산지방국토관리청 김해국토관리사무소",
      "총괄기관": "국토교통부",
      "소관구분": "국가기관",
      "합계발주금액(원)": "214,800,000",
      "발주년도": "2026",
      "발주월": "03",
      "공종구분": "",
      "계약방법": "제한경쟁",
      "조달방식": "자체조달",
      "업무유형": "신규",
      "게시일시": "2026-03-03 10:39:50",
      "담당부서": "운영지원과",
      "담당자": "김성민",
      "전화번호": "055-340-6619",
      "공고번호": "R26BK01363646000"
    },
    {
      "검색키워드": "설계",
      "사업명": "충훈대교 접속도로 옹벽 재가설공사 기본 및 실시설계용역",
      "발주기관": "경기도 광명시",
      "총괄기관": "경기도",
      "소관구분": "지방자치단체",
      "합계발주금액(원)": "203,500,000",
      "발주년도": "2026",
      "발주월": "03",
      "공종구분": "",
      "계약방법": "제한경쟁",
      "조달방식": "자체조달",
      "업무유형": "신규",
      "게시일시": "2026-03-03 17:35:44",
      "담당부서": "광명시 도로과",
      "담당자": "담당자",
      "전화번호": "02-2680-2928",
      "공고번호": "R26BK01376867000"
    },
    {
      "검색키워드": "설계",
      "사업명": "모래울동지구 연안정비사업 기본 및 실시설계용역",
      "발주기관": "인천광역시 옹진군",
      "총괄기관": "인천광역시",
      "소관구분": "지방자치단체",
      "합계발주금액(원)": "196,339,000",
      "발주년도": "2026",
      "발주월": "03",
      "공종구분": "",
      "계약방법": "제한경쟁",
      "조달방식": "자체조달",
      "업무유형": "신규",
      "게시일시": "2026-03-03 09:59:51",
      "담당부서": "해양시설과",
      "담당자": "이종호",
      "전화번호": "032-899-2681",
      "공고번호": ""
    },
    {
      "검색키워드": "설계",
      "사업명": "도시계획도로(세무서사거리~남부산단 진입도로) 도시관리계획 결정(변경) 및 기본설계 용역",
      "발주기관": "충청남도 서산시",
      "총괄기관": "충청남도",
      "소관구분": "지방자치단체",
      "합계발주금액(원)": "195,110,000",
      "발주년도": "2026",
      "발주월": "03",
      "공종구분": "",
      "계약방법": "제한경쟁",
      "조달방식": "자체조달",
      "업무유형": "신규",
      "게시일시": "2026-03-03 20:21:57",
      "담당부서": "도로과",
      "담당자": "배대원",
      "전화번호": "041-660-2445",
      "공고번호": "R26BK01366143000"
    },
    {
      "검색키워드": "설계",
      "사업명": "무지개마을 노후생활관 증개축공사 설계용역(건축)",
      "발주기관": "무지개마을",
      "총괄기관": "무지개마을",
      "소관구분": "기타기관",
      "합계발주금액(원)": "188,560,000",
      "발주년도": "2026",
      "발주월": "03",
      "공종구분": "",
      "계약방법": "지명경쟁",
      "조달방식": "자체조달",
      "업무유형": "신규",
      "게시일시": "2026-03-03 13:39:13",
      "담당부서": "사무국",
      "담당자": "김민범",
      "전화번호": "064-723-2256",
      "공고번호": "R26BK01363173003"
    },
    {
      "검색키워드": "설계",
      "사업명": "밀양역 공영주차장 조성사업 기본 및 실시설계용역",
      "발주기관": "경상남도 밀양시",
      "총괄기관": "경상남도",
      "소관구분": "지방자치단체",
      "합계발주금액(원)": "182,000,000",
      "발주년도": "2026",
      "발주월": "03",
      "공종구분": "",
      "계약방법": "제한경쟁",
      "조달방식": "자체조달",
      "업무유형": "신규",
      "게시일시": "2026-03-03 15:08:11",
      "담당부서": "회계과",
      "담당자": "박은빈",
      "전화번호": "055-359-5147",
      "공고번호": ""
    },
    {
      "검색키워드": "설계",
      "사업명": "오포대교~양촌사거리 간 도로개설공사 설계 건설사업관리 및 VE 용역",
      "발주기관": "경기도 광주시",
      "총괄기관": "경기도",
      "소관구분": "지방자치단체",
      "합계발주금액(원)": "170,480,000",
      "발주년도": "2026",
      "발주월": "03",
      "공종구분": "",
      "계약방법": "제한경쟁",
      "조달방식": "자체조달",
      "업무유형": "신규",
      "게시일시": "2026-03-03 21:40:16",
      "담당부서": "도로사업과",
      "담당자": "신건영",
      "전화번호": "031-760-2649",
      "공고번호": "R26BK01366215000"
    },
    {
      "검색키워드": "설계",
      "사업명": "대포~컨벤션 도시계획도로(대로2-1-1호선)개설공사 보완설계용역",
      "발주기관": "제주특별자치도 서귀포시",
      "총괄기관": "제주특별자치도",
      "소관구분": "지방자치단체",
      "합계발주금액(원)": "158,170,000",
      "발주년도": "2026",
      "발주월": "03",
      "공종구분": "",
      "계약방법": "제한경쟁",
      "조달방식": "자체조달",
      "업무유형": "신규",
      "게시일시": "2026-03-03 09:11:04",
      "담당부서": "총무과",
      "담당자": "오재석",
      "전화번호": "064-760-2082",
      "공고번호": "R26BK01363240000"
    },
    {
      "검색키워드": "설계",
      "사업명": "2026년 중앙버스전용차로 흐름개선 기본 및 실시설계 용역",
      "발주기관": "서울특별시",
      "총괄기관": "서울특별시",
      "소관구분": "지방자치단체",
      "합계발주금액(원)": "150,000,000",
      "발주년도": "2026",
      "발주월": "03",
      "공종구분": "",
      "계약방법": "제한경쟁",
      "조달방식": "자체조달",
      "업무유형": "신규",
      "게시일시": "2026-03-03 10:26:28",
      "담당부서": "교통운영과",
      "담당자": "강예림",
      "전화번호": "02-2133-2466",
      "공고번호": "R26BK01363603000"
    },
    {
      "검색키워드": "설계",
      "사업명": "쇳골천 정비사업 실시설계용역",
      "발주기관": "경기도 성남시 분당구",
      "총괄기관": "경기도",
      "소관구분": "지방자치단체",
      "합계발주금액(원)": "127,490,000",
      "발주년도": "2026",
      "발주월": "03",
      "공종구분": "",
      "계약방법": "제한경쟁",
      "조달방식": "자체조달",
      "업무유형": "신규",
      "게시일시": "2026-03-03 10:33:30",
      "담당부서": "분당구 구조물관리과",
      "담당자": "박성준",
      "전화번호": "031-729-7371",
      "공고번호": ""
    },
    {
      "검색키워드": "설계",
      "사업명": "수원구치소 평택지소 내진보강설계 용역",
      "발주기관": "법무부 서울지방교정청 수원구치소 평택구치지소",
      "총괄기관": "법무부",
      "소관구분": "국가기관",
      "합계발주금액(원)": "105,831,000",
      "발주년도": "2026",
      "발주월": "03",
      "공종구분": "",
      "계약방법": "제한경쟁",
      "조달방식": "자체조달",
      "업무유형": "신규",
      "게시일시": "2026-03-03 17:39:49",
      "담당부서": "평택지소 복지계",
      "담당자": "강인원",
      "전화번호": "031-650-5852",
      "공고번호": "R26BK01377689001"
    },
    {
      "검색키워드": "설계",
      "사업명": "도림고 GB해제에 따른 훼손지 복구사업 도시관리계획 결정 및 실시설계 용역",
      "발주기관": "인천광역시",
      "총괄기관": "인천광역시",
      "소관구분": "지방자치단체",
      "합계발주금액(원)": "100,588,000",
      "발주년도": "2026",
      "발주월": "03",
      "공종구분": "",
      "계약방법": "제한경쟁",
      "조달방식": "자체조달",
      "업무유형": "신규",
      "게시일시": "2026-03-03 17:25:32",
      "담당부서": "회계담당관",
      "담당자": "박선아",
      "전화번호": "032-440-2594",
      "공고번호": "R26BK01365700000"
    },
    {
      "검색키워드": "설계",
      "사업명": "2026년 작은 섬 공도방지사업 실시설계용역(독거슬도,소성남도)",
      "발주기관": "전라남도 진도군",
      "총괄기관": "전라남도",
      "소관구분": "지방자치단체",
      "합계발주금액(원)": "73,744,000",
      "발주년도": "2026",
      "발주월": "03",
      "공종구분": "",
      "계약방법": "수의계약",
      "조달방식": "자체조달",
      "업무유형": "신규",
      "게시일시": "2026-03-03 09:55:51",
      "담당부서": "해양항만과",
      "담당자": "박주송",
      "전화번호": "061-540-6466",
      "공고번호": "R26BK01377807000"
    },
    {
      "검색키워드": "설계",
      "사업명": "덕촌항 소형선부두 설치사업 기본 및 실시설계 용역",
      "발주기관": "전라남도 장흥군",
      "총괄기관": "전라남도",
      "소관구분": "지방자치단체",
      "합계발주금액(원)": "69,600,000",
      "발주년도": "2026",
      "발주월": "03",
      "공종구분": "",
      "계약방법": "수의계약",
      "조달방식": "자체조달",
      "업무유형": "신규",
      "게시일시": "2026-03-03 15:38:48",
      "담당부서": "해양수산과 항만개발팀",
      "담당자": "김정식",
      "전화번호": "061-860-6021",
      "공고번호": ""
    },
    {
      "검색키워드": "설계",
      "사업명": "2025년 덕동댐 안전진단에 따른 시설물 보수보강 실시설계용역",
      "발주기관": "경상북도 경주시 맑은물사업본부",
      "총괄기관": "경상북도",
      "소관구분": "지방자치단체",
      "합계발주금액(원)": "65,000,000",
      "발주년도": "2026",
      "발주월": "03",
      "공종구분": "",
      "계약방법": "수의계약",
      "조달방식": "자체조달",
      "업무유형": "신규",
      "게시일시": "2026-03-03 16:45:39",
      "담당부서": "수도행정과",
      "담당자": "최주락",
      "전화번호": "054-760-7811",
      "공고번호": "R26BK01365717000"
    },
    {
      "검색키워드": "설계",
      "사업명": "장성 황룡강 지방정원 조성사업(잔여사업) 실시설계용역",
      "발주기관": "전라남도 장성군",
      "총괄기관": "전라남도",
      "소관구분": "지방자치단체",
      "합계발주금액(원)": "56,048,000",
      "발주년도": "2026",
      "발주월": "03",
      "공종구분": "",
      "계약방법": "수의계약",
      "조달방식": "자체조달",
      "업무유형": "신규",
      "게시일시": "2026-03-03 21:45:32",
      "담당부서": "황룡강사업소",
      "담당자": "서운식",
      "전화번호": "061-390-7148",
      "공고번호": "R26BK01366220000"
    },
    {
      "검색키워드": "설계",
      "사업명": "장성 황룡강 지방정원 조성사업(푸른물빛정원) 실시설계용역",
      "발주기관": "전라남도 장성군",
      "총괄기관": "전라남도",
      "소관구분": "지방자치단체",
      "합계발주금액(원)": "54,933,000",
      "발주년도": "2026",
      "발주월": "03",
      "공종구분": "",
      "계약방법": "수의계약",
      "조달방식": "자체조달",
      "업무유형": "신규",
      "게시일시": "2026-03-03 21:53:09",
      "담당부서": "황룡강사업소",
      "담당자": "서운식",
      "전화번호": "061-390-7148",
      "공고번호": "R26BK01366228000"
    },
    {
      "검색키워드": "설계",
      "사업명": "장성 황룡강 지방정원 조성사업(검은숲정원) 실시설계용역",
      "발주기관": "전라남도 장성군",
      "총괄기관": "전라남도",
      "소관구분": "지방자치단체",
      "합계발주금액(원)": "54,747,000",
      "발주년도": "2026",
      "발주월": "03",
      "공종구분": "",
      "계약방법": "수의계약",
      "조달방식": "자체조달",
      "업무유형": "신규",
      "게시일시": "2026-03-03 21:49:29",
      "담당부서": "황룡강사업소",
      "담당자": "서운식",
      "전화번호": "061-390-7148",
      "공고번호": "R26BK01366224000"
    },
    {
      "검색키워드": "설계",
      "사업명": "청도군 평생학습행복관 증축 공사 설계용역",
      "발주기관": "대구한의대학교",
      "총괄기관": "교육부",
      "소관구분": "기타기관",
      "합계발주금액(원)": "49,000,000",
      "발주년도": "2026",
      "발주월": "03",
      "공종구분": "",
      "계약방법": "제한경쟁",
      "조달방식": "자체조달",
      "업무유형": "신규",
      "게시일시": "2026-03-03 16:56:27",
      "담당부서": "경리팀",
      "담당자": "유나래",
      "전화번호": "053-819-1067",
      "공고번호": "R26BK01365559000"
    },
    {
      "검색키워드": "설계",
      "사업명": "전통시장 및 상점가 시설현대화 사업(조금시장 관리동 리모델링 및 시설보수) 실시설계 용역",
      "발주기관": "전라남도 진도군",
      "총괄기관": "전라남도",
      "소관구분": "지방자치단체",
      "합계발주금액(원)": "46,400,000",
      "발주년도": "2026",
      "발주월": "03",
      "공종구분": "",
      "계약방법": "수의계약",
      "조달방식": "자체조달",
      "업무유형": "신규",
      "게시일시": "2026-03-03 13:30:29",
      "담당부서": "경제에너지과",
      "담당자": "이상근",
      "전화번호": "061-540-6423",
      "공고번호": "R26BK01364233000"
    },
    {
      "검색키워드": "설계",
      "사업명": "고금 역사공간 관광자원 활성화사업(역사둘레길 조성) 기본 및 실시설계 용역",
      "발주기관": "전라남도 완도군",
      "총괄기관": "전라남도",
      "소관구분": "지방자치단체",
      "합계발주금액(원)": "46,200,000",
      "발주년도": "2026",
      "발주월": "03",
      "공종구분": "",
      "계약방법": "수의계약",
      "조달방식": "자체조달",
      "업무유형": "신규",
      "게시일시": "2026-03-03 23:20:28",
      "담당부서": "문화예술과",
      "담당자": "김진보",
      "전화번호": "061-550-5467",
      "공고번호": ""
    },
    {
      "검색키워드": "설계",
      "사업명": "성산구 양곡동 봉산마을 일원 하수관로 정비공사 실시설계용역",
      "발주기관": "경상남도 창원시 하수도사업소",
      "총괄기관": "경상남도",
      "소관구분": "지방자치단체",
      "합계발주금액(원)": "46,180,000",
      "발주년도": "2026",
      "발주월": "03",
      "공종구분": "",
      "계약방법": "수의계약",
      "조달방식": "자체조달",
      "업무유형": "신규",
      "게시일시": "2026-03-03 17:15:07",
      "담당부서": "하수시설과",
      "담당자": "이상권",
      "전화번호": "055-225-2885",
      "공고번호": ""
    },
    {
      "검색키워드": "설계",
      "사업명": "2026년 서울시 어린이 보호구역 교통신호기 설치공사 실시설계 용역",
      "발주기관": "서울특별시",
      "총괄기관": "서울특별시",
      "소관구분": "지방자치단체",
      "합계발주금액(원)": "43,846,000",
      "발주년도": "2026",
      "발주월": "03",
      "공종구분": "",
      "계약방법": "제한경쟁",
      "조달방식": "자체조달",
      "업무유형": "신규",
      "게시일시": "2026-03-03 09:58:34",
      "담당부서": "보행자전거과",
      "담당자": "송선훈",
      "전화번호": "02-2133-2430",
      "공고번호": "R26BK01363449000"
    },
    {
      "검색키워드": "설계",
      "사업명": "국도59호선 산청 금서매촌 병목지점 개선공사 실시설계용역",
      "발주기관": "경상남도 서부도로관리사업소",
      "총괄기관": "경상남도",
      "소관구분": "지방자치단체",
      "합계발주금액(원)": "42,910,000",
      "발주년도": "2026",
      "발주월": "03",
      "공종구분": "",
      "계약방법": "수의계약",
      "조달방식": "자체조달",
      "업무유형": "신규",
      "게시일시": "2026-03-03 16:15:59",
      "담당부서": "경상남도 서부도로관리사업소",
      "담당자": "우민기",
      "전화번호": "055-254-4244",
      "공고번호": "R26BK01369010000"
    },
    {
      "검색키워드": "설계",
      "사업명": "2026년 봉수산 자연휴양림 데크보행로 교체사업 실시설계용역",
      "발주기관": "충청남도 예산군",
      "총괄기관": "충청남도",
      "소관구분": "지방자치단체",
      "합계발주금액(원)": "31,028,000",
      "발주년도": "2026",
      "발주월": "03",
      "공종구분": "",
      "계약방법": "수의계약",
      "조달방식": "자체조달",
      "업무유형": "신규",
      "게시일시": "2026-03-03 19:40:15",
      "담당부서": "회계과",
      "담당자": "한건일",
      "전화번호": "041-339-7399",
      "공고번호": "R26BK01366067000"
    },
    {
      "검색키워드": "설계",
      "사업명": "장성호 수변백리길(숲속길) 임도개설 공사(2구간) 실시설계용역",
      "발주기관": "전라남도 장성군",
      "총괄기관": "전라남도",
      "소관구분": "지방자치단체",
      "합계발주금액(원)": "29,042,000",
      "발주년도": "2026",
      "발주월": "03",
      "공종구분": "",
      "계약방법": "수의계약",
      "조달방식": "자체조달",
      "업무유형": "신규",
      "게시일시": "2026-03-03 16:05:27",
      "담당부서": "관광과",
      "담당자": "심현우",
      "전화번호": "061-390-7403",
      "공고번호": "R26BK01365205000"
    },
    {
      "검색키워드": "설계",
      "사업명": "영암 죽정마을 옛담장 보수 실시설계용역",
      "발주기관": "전라남도 영암군",
      "총괄기관": "전라남도",
      "소관구분": "지방자치단체",
      "합계발주금액(원)": "27,900,000",
      "발주년도": "2026",
      "발주월": "03",
      "공종구분": "",
      "계약방법": "수의계약",
      "조달방식": "자체조달",
      "업무유형": "신규",
      "게시일시": "2026-03-03 15:18:06",
      "담당부서": "문화예술과",
      "담당자": "김수인",
      "전화번호": "061-470-2637",
      "공고번호": "R26BK01367140000"
    },
    {
      "검색키워드": "설계",
      "사업명": "2026년 지방하천  유지관리사업 실시설계 용역",
      "발주기관": "전라남도 장흥군",
      "총괄기관": "전라남도",
      "소관구분": "지방자치단체",
      "합계발주금액(원)": "27,000,000",
      "발주년도": "2026",
      "발주월": "03",
      "공종구분": "",
      "계약방법": "수의계약",
      "조달방식": "자체조달",
      "업무유형": "신규",
      "게시일시": "2026-03-03 08:53:36",
      "담당부서": "재난안전과",
      "담당자": "이승환",
      "전화번호": "061-860-6197",
      "공고번호": "R26BK01363192000"
    },
    {
      "검색키워드": "설계",
      "사업명": "2026년 산불대응센터(호산) 실시설계용역",
      "발주기관": "산림청 동부지방산림청 삼척국유림관리소",
      "총괄기관": "산림청",
      "소관구분": "국가기관",
      "합계발주금액(원)": "21,992,000",
      "발주년도": "2026",
      "발주월": "03",
      "공종구분": "",
      "계약방법": "수의계약",
      "조달방식": "자체조달",
      "업무유형": "신규",
      "게시일시": "2026-03-03 15:07:36",
      "담당부서": "산림재난대응팀",
      "담당자": "신중권",
      "전화번호": "033-570-5251",
      "공고번호": "R26BK01366853000"
    },
    {
      "검색키워드": "설계",
      "사업명": "호명 피실천 정비공사 외 2개지구 실시설계 용역 ",
      "발주기관": "경상북도 예천군",
      "총괄기관": "경상북도",
      "소관구분": "지방자치단체",
      "합계발주금액(원)": "21,600,000",
      "발주년도": "2026",
      "발주월": "03",
      "공종구분": "",
      "계약방법": "수의계약",
      "조달방식": "자체조달",
      "업무유형": "신규",
      "게시일시": "2026-03-03 16:45:12",
      "담당부서": "안전재난과",
      "담당자": "이인우",
      "전화번호": "054-650-6918",
      "공고번호": ""
    },
    {
      "검색키워드": "설계",
      "사업명": "물놀이장 폭염저감시설(쿨링포그) 설치 실시설계 용역",
      "발주기관": "경기도 하남시",
      "총괄기관": "경기도",
      "소관구분": "지방자치단체",
      "합계발주금액(원)": "21,578,000",
      "발주년도": "2026",
      "발주월": "03",
      "공종구분": "",
      "계약방법": "수의계약",
      "조달방식": "자체조달",
      "업무유형": "신규",
      "게시일시": "2026-03-03 12:24:30",
      "담당부서": "공원녹지과",
      "담당자": "전성민",
      "전화번호": "031-790-5145",
      "공고번호": ""
    },
    {
      "검색키워드": "설계",
      "사업명": "용문 뒷내천 정비공사 외 1개지구 실시설계 용역 ",
      "발주기관": "경상북도 예천군",
      "총괄기관": "경상북도",
      "소관구분": "지방자치단체",
      "합계발주금액(원)": "20,300,000",
      "발주년도": "2026",
      "발주월": "03",
      "공종구분": "",
      "계약방법": "수의계약",
      "조달방식": "자체조달",
      "업무유형": "신규",
      "게시일시": "2026-03-03 16:18:58",
      "담당부서": "안전재난과",
      "담당자": "이인우",
      "전화번호": "054-650-6918",
      "공고번호": ""
    },
    {
      "검색키워드": "설계",
      "사업명": "2026년 임도구조개량사업 실시설계용역(싸리재 외 1)",
      "발주기관": "산림청 동부지방산림청 태백국유림관리소",
      "총괄기관": "산림청",
      "소관구분": "국가기관",
      "합계발주금액(원)": "19,243,000",
      "발주년도": "2026",
      "발주월": "03",
      "공종구분": "",
      "계약방법": "수의계약",
      "조달방식": "자체조달",
      "업무유형": "신규",
      "게시일시": "2026-03-03 13:07:03",
      "담당부서": "보호산사태팀",
      "담당자": "이상철",
      "전화번호": "033-550-9931",
      "공고번호": ""
    },
    {
      "검색키워드": "설계",
      "사업명": "은풍 부초천 정비공사 외 1개지구 실시설계 용역 ",
      "발주기관": "경상북도 예천군",
      "총괄기관": "경상북도",
      "소관구분": "지방자치단체",
      "합계발주금액(원)": "19,200,000",
      "발주년도": "2026",
      "발주월": "03",
      "공종구분": "",
      "계약방법": "수의계약",
      "조달방식": "자체조달",
      "업무유형": "신규",
      "게시일시": "2026-03-03 18:04:44",
      "담당부서": "안전재난과",
      "담당자": "이인우",
      "전화번호": "054-650-6918",
      "공고번호": ""
    },
    {
      "검색키워드": "설계",
      "사업명": "보문 수계2리(장수골)마을안길 아스콘 덧씌우기공사 외 2개지구 실시설계용역 ",
      "발주기관": "경상북도 예천군",
      "총괄기관": "경상북도",
      "소관구분": "지방자치단체",
      "합계발주금액(원)": "19,000,000",
      "발주년도": "2026",
      "발주월": "03",
      "공종구분": "",
      "계약방법": "수의계약",
      "조달방식": "자체조달",
      "업무유형": "신규",
      "게시일시": "2026-03-03 18:24:03",
      "담당부서": "건설교통과",
      "담당자": "여태산",
      "전화번호": "054-650-6097",
      "공고번호": ""
    },
    {
      "검색키워드": "설계",
      "사업명": "2026년 임도구조개량사업 실시설계용역(풀장골 외 1)",
      "발주기관": "산림청 동부지방산림청 태백국유림관리소",
      "총괄기관": "산림청",
      "소관구분": "국가기관",
      "합계발주금액(원)": "18,164,000",
      "발주년도": "2026",
      "발주월": "03",
      "공종구분": "",
      "계약방법": "수의계약",
      "조달방식": "자체조달",
      "업무유형": "신규",
      "게시일시": "2026-03-03 13:39:35",
      "담당부서": "보호산사태팀",
      "담당자": "이상철",
      "전화번호": "033-550-9931",
      "공고번호": ""
    },
    {
      "검색키워드": "설계",
      "사업명": "서라벌초등학교 본관동 외벽개선공사 설계용역",
      "발주기관": "경상북도교육청 경상북도경주교육지원청",
      "총괄기관": "경상북도교육청",
      "소관구분": "교육기관",
      "합계발주금액(원)": "15,627,000",
      "발주년도": "2026",
      "발주월": "03",
      "공종구분": "",
      "계약방법": "수의계약",
      "조달방식": "자체조달",
      "업무유형": "신규",
      "게시일시": "2026-03-03 13:24:03",
      "담당부서": "행정지원과",
      "담당자": "이한솔",
      "전화번호": "054-740-9132",
      "공고번호": "R26BK01364160000"
    },
    {
      "검색키워드": "설계",
      "사업명": "예천 왕신1리(신천서원앞) 농로 확포장공사 외 2개지구 실시설계용역 ",
      "발주기관": "경상북도 예천군",
      "총괄기관": "경상북도",
      "소관구분": "지방자치단체",
      "합계발주금액(원)": "14,400,000",
      "발주년도": "2026",
      "발주월": "03",
      "공종구분": "",
      "계약방법": "수의계약",
      "조달방식": "자체조달",
      "업무유형": "신규",
      "게시일시": "2026-03-03 18:11:49",
      "담당부서": "건설교통과",
      "담당자": "김억구",
      "전화번호": "054-650-6338",
      "공고번호": ""
    },
    {
      "검색키워드": "설계",
      "사업명": "2026년 굴착복구 노면표시 설계 및 건설사업관리용역-서부",
      "발주기관": "서울특별시 도로사업소 서부도로사업소",
      "총괄기관": "서울특별시",
      "소관구분": "지방자치단체",
      "합계발주금액(원)": "14,342,900",
      "발주년도": "2026",
      "발주월": "03",
      "공종구분": "",
      "계약방법": "수의계약",
      "조달방식": "자체조달",
      "업무유형": "신규",
      "게시일시": "2026-03-03 10:57:06",
      "담당부서": "도로보수과",
      "담당자": "정병구",
      "전화번호": "02-300-8351",
      "공고번호": "R26BK01363744000"
    },
    {
      "검색키워드": "설계",
      "사업명": "2026년 임도구조개량사업 실시설계용역(싸리밭골)",
      "발주기관": "산림청 동부지방산림청 태백국유림관리소",
      "총괄기관": "산림청",
      "소관구분": "국가기관",
      "합계발주금액(원)": "13,497,000",
      "발주년도": "2026",
      "발주월": "03",
      "공종구분": "",
      "계약방법": "수의계약",
      "조달방식": "자체조달",
      "업무유형": "신규",
      "게시일시": "2026-03-03 13:20:59",
      "담당부서": "보호산사태팀",
      "담당자": "이상철",
      "전화번호": "033-550-9931",
      "공고번호": ""
    },
    {
      "검색키워드": "설계",
      "사업명": "2026년 임도구조개량사업 실시설계용역(절골)",
      "발주기관": "산림청 동부지방산림청 태백국유림관리소",
      "총괄기관": "산림청",
      "소관구분": "국가기관",
      "합계발주금액(원)": "13,497,000",
      "발주년도": "2026",
      "발주월": "03",
      "공종구분": "",
      "계약방법": "수의계약",
      "조달방식": "자체조달",
      "업무유형": "신규",
      "게시일시": "2026-03-03 13:13:14",
      "담당부서": "보호산사태팀",
      "담당자": "이상철",
      "전화번호": "033-550-9931",
      "공고번호": ""
    },
    {
      "검색키워드": "설계",
      "사업명": "2026년 임도구조개량사업 실시설계용역(사내골)",
      "발주기관": "산림청 동부지방산림청 태백국유림관리소",
      "총괄기관": "산림청",
      "소관구분": "국가기관",
      "합계발주금액(원)": "12,726,000",
      "발주년도": "2026",
      "발주월": "03",
      "공종구분": "",
      "계약방법": "수의계약",
      "조달방식": "자체조달",
      "업무유형": "신규",
      "게시일시": "2026-03-03 13:35:37",
      "담당부서": "보호산사태팀",
      "담당자": "이상철",
      "전화번호": "033-550-9931",
      "공고번호": ""
    },
    {
      "검색키워드": "설계",
      "사업명": "중산중 3층 보통교실 후로링교체공사 설계용역",
      "발주기관": "경기도교육청 경기도고양교육지원청 중산중학교",
      "총괄기관": "경기도교육청",
      "소관구분": "교육기관",
      "합계발주금액(원)": "7,700,000",
      "발주년도": "2026",
      "발주월": "03",
      "공종구분": "",
      "계약방법": "수의계약",
      "조달방식": "자체조달",
      "업무유형": "신규",
      "게시일시": "2026-03-03 10:48:56",
      "담당부서": "교육행정실",
      "담당자": "이정빈",
      "전화번호": "031-960-6371",
      "공고번호": ""
    },
    {
      "검색키워드": "설계",
      "사업명": "상당산성 진입로 확장공사 전기공사(2단계) 실시설계용역",
      "발주기관": "충청북도 청주시",
      "총괄기관": "충청북도",
      "소관구분": "지방자치단체",
      "합계발주금액(원)": "5,300,000",
      "발주년도": "2026",
      "발주월": "03",
      "공종구분": "",
      "계약방법": "수의계약",
      "조달방식": "자체조달",
      "업무유형": "신규",
      "게시일시": "2026-03-03 16:09:00",
      "담당부서": "도로시설과",
      "담당자": "신관섭",
      "전화번호": "043-201-2773",
      "공고번호": ""
    },
    {
      "검색키워드": "설계",
      "사업명": "남산1동 행정복지센터 건립 설계공모 심사 실시간 중계 용역",
      "발주기관": "대구광역시 중구",
      "총괄기관": "대구광역시",
      "소관구분": "지방자치단체",
      "합계발주금액(원)": "2,200,000",
      "발주년도": "2026",
      "발주월": "03",
      "공종구분": "",
      "계약방법": "수의계약",
      "조달방식": "자체조달",
      "업무유형": "신규",
      "게시일시": "2026-03-03 19:39:23",
      "담당부서": "건축주택과",
      "담당자": "서원철",
      "전화번호": "053-661-2953",
      "공고번호": ""
    },
    {
      "검색키워드": "설계",
      "사업명": "서울강남지부 인테리어공사 설계 용역",
      "발주기관": "한국건강관리협회",
      "총괄기관": "한국건강관리협회",
      "소관구분": "기타기관",
      "합계발주금액(원)": "111",
      "발주년도": "2026",
      "발주월": "03",
      "공종구분": "",
      "계약방법": "제한경쟁",
      "조달방식": "자체조달",
      "업무유형": "신규",
      "게시일시": "2026-03-03 08:07:15",
      "담당부서": "운영관리본부",
      "담당자": "서준혁",
      "전화번호": "02-2600-0130",
      "공고번호": "R26BK01363141000"
    },
    {
      "검색키워드": "건설사업관리",
      "사업명": "의정부법조타운 A-3BL 및 S-1BL 아파트 건설공사 시공단게 감독권한대행 등 (통합)건설사업관리용역",
      "발주기관": "한국토지주택공사",
      "총괄기관": "한국토지주택공사",
      "소관구분": "공기업",
      "합계발주금액(원)": "17,379,352,000",
      "발주년도": "2026",
      "발주월": "03",
      "공종구분": "",
      "계약방법": "일반경쟁",
      "조달방식": "중앙조달",
      "업무유형": "신규",
      "게시일시": "2026-03-03 20:15:59",
      "담당부서": "주택품질안전처",
      "담당자": "박경만",
      "전화번호": "055-922-5415",
      "공고번호": ""
    },
    {
      "검색키워드": "건설사업관리",
      "사업명": " 서주·한남 자연재해위험개선지구 정비사업 건설사업관리용역",
      "발주기관": "경상남도 함양군",
      "총괄기관": "경상남도",
      "소관구분": "지방자치단체",
      "합계발주금액(원)": "5,670,654,000",
      "발주년도": "2026",
      "발주월": "03",
      "공종구분": "",
      "계약방법": "지명경쟁",
      "조달방식": "자체조달",
      "업무유형": "신규",
      "게시일시": "2026-03-03 17:00:37",
      "담당부서": "안전총괄과",
      "담당자": "복구지원담당",
      "전화번호": "055-960-4323",
      "공고번호": "R26BK01365576000"
    },
    {
      "검색키워드": "건설사업관리",
      "사업명": "백전 자연재해위험개선지구 정비사업 건설사업관리용역",
      "발주기관": "경상남도 함양군",
      "총괄기관": "경상남도",
      "소관구분": "지방자치단체",
      "합계발주금액(원)": "4,128,553,000",
      "발주년도": "2026",
      "발주월": "03",
      "공종구분": "",
      "계약방법": "지명경쟁",
      "조달방식": "자체조달",
      "업무유형": "신규",
      "게시일시": "2026-03-03 16:47:42",
      "담당부서": "안전총괄과",
      "담당자": "복구지원담당",
      "전화번호": "055-960-4323",
      "공고번호": "R26BK01365479000"
    },
    {
      "검색키워드": "건설사업관리",
      "사업명": "(가칭)송담고등학교 신축공사 건설사업관리용역",
      "발주기관": "경기도교육청",
      "총괄기관": "경기도교육청",
      "소관구분": "교육기관",
      "합계발주금액(원)": "3,527,425,000",
      "발주년도": "2026",
      "발주월": "03",
      "공종구분": "",
      "계약방법": "일반경쟁",
      "조달방식": "중앙조달",
      "업무유형": "신규",
      "게시일시": "2026-03-03 15:56:15",
      "담당부서": "재무관리과",
      "담당자": "이지은",
      "전화번호": "031-249-0392",
      "공고번호": ""
    },
    {
      "검색키워드": "건설사업관리",
      "사업명": "산척지구풍수해생활권종합정비사업건설사업관리용역",
      "발주기관": "충청북도 충주시",
      "총괄기관": "충청북도",
      "소관구분": "지방자치단체",
      "합계발주금액(원)": "2,355,000,000",
      "발주년도": "2026",
      "발주월": "03",
      "공종구분": "",
      "계약방법": "일반경쟁",
      "조달방식": "자체조달",
      "업무유형": "신규",
      "게시일시": "2026-03-03 17:00:55",
      "담당부서": "회계과",
      "담당자": "조희연",
      "전화번호": "043-850-5625",
      "공고번호": "R26BK01365473000"
    },
    {
      "검색키워드": "건설사업관리",
      "사업명": "백연리 농어촌마을하수도 정비사업 건설사업관리용역",
      "발주기관": "경기도 파주시",
      "총괄기관": "경기도",
      "소관구분": "지방자치단체",
      "합계발주금액(원)": "2,312,953,000",
      "발주년도": "2026",
      "발주월": "03",
      "공종구분": "",
      "계약방법": "일반경쟁",
      "조달방식": "자체조달",
      "업무유형": "장기",
      "게시일시": "2026-03-03 15:07:49",
      "담당부서": "하수도과",
      "담당자": "조하나",
      "전화번호": "031-940-5227",
      "공고번호": ""
    },
    {
      "검색키워드": "건설사업관리",
      "사업명": "노원구 하수도분야 건설사업관리(전문감리) 용역",
      "발주기관": "서울특별시 노원구",
      "총괄기관": "서울특별시",
      "소관구분": "지방자치단체",
      "합계발주금액(원)": "716,450,000",
      "발주년도": "2026",
      "발주월": "03",
      "공종구분": "",
      "계약방법": "일반경쟁",
      "조달방식": "자체조달",
      "업무유형": "신규",
      "게시일시": "2026-03-03 10:20:39",
      "담당부서": "치수과",
      "담당자": "배수오",
      "전화번호": "02-2116-4192",
      "공고번호": "R26BK01376579000"
    },
    {
      "검색키워드": "건설사업관리",
      "사업명": "2026-2027년 성북구 하수도분야 건설사업관리(전문감리) 용역 시행(긴급)",
      "발주기관": "서울특별시 성북구",
      "총괄기관": "서울특별시",
      "소관구분": "지방자치단체",
      "합계발주금액(원)": "700,000,000",
      "발주년도": "2026",
      "발주월": "03",
      "공종구분": "",
      "계약방법": "일반경쟁",
      "조달방식": "자체조달",
      "업무유형": "장기",
      "게시일시": "2026-03-03 11:34:38",
      "담당부서": "치수과",
      "담당자": "김수영",
      "전화번호": "02-2241-3632",
      "공고번호": "R26BK01376423000"
    },
    {
      "검색키워드": "건설사업관리",
      "사업명": "2026~2027년 강동구 하수도분야 전문감리(건설사업관리) 용역-장기계속",
      "발주기관": "서울특별시 강동구",
      "총괄기관": "서울특별시",
      "소관구분": "지방자치단체",
      "합계발주금액(원)": "700,000,000",
      "발주년도": "2026",
      "발주월": "03",
      "공종구분": "",
      "계약방법": "일반경쟁",
      "조달방식": "자체조달",
      "업무유형": "장기",
      "게시일시": "2026-03-03 13:35:12",
      "담당부서": "치수과",
      "담당자": "강유돈",
      "전화번호": "02-3425-6402",
      "공고번호": ""
    },
    {
      "검색키워드": "건설사업관리",
      "사업명": "2026~2027년 하수도 건설사업관리 용역",
      "발주기관": "서울특별시 강북구",
      "총괄기관": "서울특별시",
      "소관구분": "지방자치단체",
      "합계발주금액(원)": "700,000,000",
      "발주년도": "2026",
      "발주월": "03",
      "공종구분": "",
      "계약방법": "일반경쟁",
      "조달방식": "자체조달",
      "업무유형": "신규",
      "게시일시": "2026-03-03 13:33:20",
      "담당부서": "치수과",
      "담당자": "이종명",
      "전화번호": "02-901-5882",
      "공고번호": "R26BK01365123000,R26BK01364310001"
    },
    {
      "검색키워드": "건설사업관리",
      "사업명": "평택·당진항 국제여객터미널 소방시설 유지보수설비(캣워크) 설치공사 건설사업관리용역",
      "발주기관": "해양수산부 평택지방해양수산청",
      "총괄기관": "해양수산부",
      "소관구분": "국가기관",
      "합계발주금액(원)": "170,000,000",
      "발주년도": "2026",
      "발주월": "03",
      "공종구분": "",
      "계약방법": "제한경쟁",
      "조달방식": "자체조달",
      "업무유형": "신규",
      "게시일시": "2026-03-03 15:11:46",
      "담당부서": "운영지원과",
      "담당자": "황유진",
      "전화번호": "031-680-7208",
      "공고번호": "R26BK01378765000"
    }
  ]
}